setup.py
pyadmitad/__init__.py
pyadmitad/api.py
pyadmitad/client.py
pyadmitad/constants.py
pyadmitad/exceptions.py
pyadmitad/transport.py
pyadmitad/items/__init__.py
pyadmitad/items/announcements.py
pyadmitad/items/auxiliary.py
pyadmitad/items/banners.py
pyadmitad/items/base.py
pyadmitad/items/campaigns.py
pyadmitad/items/coupons.py
pyadmitad/items/me.py
pyadmitad/items/payments.py
pyadmitad/items/products.py
pyadmitad/items/referrals.py
pyadmitad/items/statistics.py
pyadmitad/items/websites.py
pyadmitad/tests/__init__.py
pyadmitad/tests/base.py
pyadmitad/tests/test_announcements.py
pyadmitad/tests/test_auxiliary.py
pyadmitad/tests/test_banners.py
pyadmitad/tests/test_campaigns.py
pyadmitad/tests/test_coupons.py
pyadmitad/tests/test_me.py
pyadmitad/tests/test_payments.py
pyadmitad/tests/test_products.py
pyadmitad/tests/test_referrals.py
pyadmitad/tests/test_statistics.py
pyadmitad/tests/test_websites.py
pyadmitad_unknown.egg-info/PKG-INFO
pyadmitad_unknown.egg-info/SOURCES.txt
pyadmitad_unknown.egg-info/dependency_links.txt
pyadmitad_unknown.egg-info/requires.txt
pyadmitad_unknown.egg-info/top_level.txt